{
    "name": "Copper",
    "is_dark": true,
    "colors": {
        "accent-color": "#D1AB49",
        "primary-color": "#33B5B5",
        "warning-color": "#CC4444",
        "sidebar-color": "#1A2A2A",
        "roomlist-background-color": "#1A2A2A",
        "roomlist-text-color": "#E6F2F2",
        "roomlist-text-secondary-color": "#809090",
        "roomlist-highlights-color": "#D1AB49",
        "timeline-background-color": "#0D1C1C",
        "timeline-text-color": "#E6F2F2",
        "secondary-content": "#007777",
        "tertiary-content": "#003D3D",
        "timeline-text-secondary-color": "#809090",
        "timeline-highlights-color": "#33B5B5",
        "reaction-row-button-selected-bg-color": "#D1AB49"
    }
}
